mrst/__init__.py
mrst/build.py
mrst/cli.py
mrst/common.py
mrst/cpp.py
mrst/gen.py
mrst/version.py
mrst-0.6.1.dist-info/entry_points.txt
mrst-0.6.1.dist-info/WHEEL
mrst-0.6.1.dist-info/METADATA
mrst-0.6.1.dist-info/RECORD
